[
    { 
        "id": 1, 
        "friendId": 1, 
        "friendName": "mijin", 
        "userId": "kimmj5678", 
        "addDate": "2024-01-15" 
    },
    { 
        "id": 2, 
        "friendId": 2, 
        "friendName": "sieun", 
        "userId": "kose0987", 
        "addDate": "2024-01-20" 
    },
    { 
        "id": 3, 
        "friendId": 3, 
        "friendName": "seorin", 
        "userId": "chaesr6543", 
        "addDate": "2024-01-25" 
    },
    { 
        "id": 4, 
        "friendId": 4, 
        "friendName": "seyeon", 
        "userId": "imsy2109", 
        "addDate": "2024-02-01" 
    },
    { 
        "id": 5, 
        "friendId": 5, 
        "friendName": "hyeri", 
        "userId": "janghr8765", 
        "addDate": "2024-02-05" 
    }
]
